{
  "project_info": {
    "project_number": "1007593972465",
    "project_id": "mobileappflutter-cc308",
    "storage_bucket": "mobileappflutter-cc308.firebasestorage.app"
  },
  "client": [
    {
      "client_info": {
        "mobilesdk_app_id": "1:1007593972465:android:c8a82f66866b9ca4df7f50",
        "android_client_info": {
          "package_name": "com.example.mobileapp"
        }
      },
      "oauth_client": [],
      "api_key": [
        {
          "current_key": "AIzaSyCyAE8c0YIUEsB8PJMJgiaXvOWkjjhV9Og"
        }
      ],
      "services": {
        "appinvite_service": {
          "other_platform_oauth_client": []
        }
      }
    }
  ],
  "configuration_version": "1"
}